qiskit_shots_animator/__init__.py
qiskit_shots_animator/visualization/__init__.py
qiskit_shots_animator/visualization/animate_shots.py
qiskit_shots_animator/visualization/resources/__init__.py
qiskit_shots_animator/visualization/resources/albatross.png
qiskit_shots_animator/visualization/resources/giraffe.png
qiskit_shots_animator/visualization/resources/snake.png
qiskit_shots_animator/visualization/resources/sparrow.png
qiskit_shots_animator/visualization/resources/sparrow_xray_labelled.png
qiskit_shots_animator/visualization/resources/sparrow_xray_unlabelled.png
qiskit_shots_animator/visualization/resources/unknown20a.png
qiskit_shots_animator/visualization/resources/unknown20b.png
qiskit_shots_animator/visualization/resources/unknown53a.png
qiskit_shots_animator-1.0.1.dist-info/LICENSE
qiskit_shots_animator-1.0.1.dist-info/METADATA
qiskit_shots_animator-1.0.1.dist-info/WHEEL
qiskit_shots_animator-1.0.1.dist-info/top_level.txt
qiskit_shots_animator-1.0.1.dist-info/RECORD
