Metadata-Version: 2.1
Name: qiskit-shots-animator
Version: 1.0.1
Summary: Software for animating quantum computing programs
Home-page: https://github.com/teavuihuang/qiskit-shots-animator
Author: Tea Vui Huang
Author-email: tvhuang@hotmail.com
License: Apache 2.0
Keywords: qiskit sdk quantum animation
Platform: UNKNOWN
Classifier: Environment :: Console
Classifier: License :: OSI Approved :: Apache Software License
Classifier: Intended Audience :: Developers
Classifier: Intended Audience :: Science/Research
Classifier: Operating System :: Microsoft :: Windows
Classifier: Operating System :: MacOS
Classifier: Operating System :: POSIX :: Linux
Classifier: Programming Language :: Python :: 3.6
Classifier: Programming Language :: Python :: 3.7
Classifier: Programming Language :: Python :: 3.8
Classifier: Topic :: Scientific/Engineering
Requires-Python: >=3.6
Requires-Dist: matplotlib (>=3.2.2)
Requires-Dist: numpy (>=1.18.5)
Requires-Dist: pillow (>=7.2.0)
Requires-Dist: pkginfo (>=1.5.0.1)
